fugue_incubator/__init__.py
fugue_incubator_version/__init__.py
fugue_ml/__init__.py
fugue_tune/__init__.py
fugue_tune/constants.py
fugue_tune/exceptions.py
fugue_tune/hyperopt.py
fugue_tune/iter.py
fugue_tune/sklearn.py
fugue_tune/space.py
fugue_tune/tune.py
fugue_tune/utils.py
fugue_tune/pruners/__init__.py
tests/__init__.py
tests/fugue_tune/__init__.py
tests/fugue_tune/test_convert.py
tests/fugue_tune/test_hyperopt.py
tests/fugue_tune/test_iter.py
tests/fugue_tune/test_sklearn.py
tests/fugue_tune/test_space.py
tests/fugue_tune/test_tunable.py
tests/fugue_tune/test_tune.py
tests/fugue_tune/test_utils.py
fugue_incubator-0.0.8.dist-info/LICENSE
fugue_incubator-0.0.8.dist-info/METADATA
fugue_incubator-0.0.8.dist-info/WHEEL
fugue_incubator-0.0.8.dist-info/top_level.txt
fugue_incubator-0.0.8.dist-info/RECORD
